pykh/__init__.py
pykh/python_kuberhealthy.py
python_kuberhealthy-0.0.6.dist-info/LICENSE
python_kuberhealthy-0.0.6.dist-info/METADATA
python_kuberhealthy-0.0.6.dist-info/WHEEL
python_kuberhealthy-0.0.6.dist-info/top_level.txt
python_kuberhealthy-0.0.6.dist-info/RECORD
