Metadata-Version: 2.1
Name: python-kuberhealthy
Version: 0.0.6
Summary: Simple Kuberhealthy python client
Home-page: UNKNOWN
Author: Francisco Meza
Author-email: mezafrank04@gmail.com
License: UNKNOWN
Platform: UNKNOWN
Classifier: Programming Language :: Python :: 3
Classifier: License :: OSI Approved :: MIT License
Classifier: Operating System :: OS Independent
Requires-Python: >=3.6
